{"nm":"LOGO ANIMATION 1 final","ddd":0,"h":1080,"w":1920,"meta":{"g":"LottieFiles AE 3.5.4"},"layers":[{"ty":4,"nm":"Shape Layer 1","sr":1,"st":0,"op":225,"ip":0,"hd":false,"ddd":0,"bm":0,"hasMask":false,"td":1,"ao":0,"ks":{"a":{"a":0,"k":[0,0,0],"ix":1},"s":{"a":0,"k":[100,100,100],"ix":6},"sk":{"a":0,"k":0},"p":{"a":0,"k":[960,267.25,0],"ix":2},"r":{"a":0,"k":0,"ix":10},"sa":{"a":0,"k":0},"o":{"a":0,"k":100,"ix":11}},"ef":[],"shapes":[{"ty":"gr","bm":0,"hd":false,"mn":"ADBE Vector Group","nm":"Rectangle 1","ix":1,"cix":2,"np":3,"it":[{"ty":"rc","bm":0,"hd":false,"mn":"ADBE Vector Shape - Rect","nm":"Rectangle Path 1","d":1,"p":{"a":0,"k":[0,0],"ix":3},"r":{"a":0,"k":0,"ix":4},"s":{"a":0,"k":[388.859,272.891],"ix":2}},{"ty":"fl","bm":0,"hd":false,"mn":"ADBE Vector Graphic - Fill","nm":"Fill 1","c":{"a":0,"k":[0.9569,0.9569,0.9569],"ix":4},"r":1,"o":{"a":0,"k":100,"ix":5}},{"ty":"tr","a":{"a":0,"k":[0,0],"ix":1},"s":{"a":0,"k":[100,100],"ix":3},"sk":{"a":0,"k":0,"ix":4},"p":{"a":0,"k":[28.43,211.445],"ix":2},"r":{"a":0,"k":0,"ix":6},"sa":{"a":0,"k":0,"ix":5},"o":{"a":0,"k":100,"ix":7}}]}],"ind":1},{"ty":0,"nm":"Pre-comp 1","sr":1,"st":-201,"op":3399,"ip":-201,"hd":false,"ddd":0,"bm":0,"tt":1,"hasMask":false,"ao":0,"ks":{"a":{"a":0,"k":[960,540,0],"ix":1},"s":{"a":0,"k":[100,100,100],"ix":6},"sk":{"a":0,"k":0},"p":{"a":1,"k":[{"o":{"x":0.8,"y":0},"i":{"x":0.192,"y":1},"s":[960,692,0],"t":3,"ti":[0,0,0],"to":[0,0,0]},{"s":[960,540,0],"t":60}],"ix":2},"r":{"a":0,"k":0,"ix":10},"sa":{"a":0,"k":0},"o":{"a":0,"k":100,"ix":11}},"ef":[],"w":1920,"h":1080,"refId":"comp_0","ind":2}],"v":"4.8.0","fr":60,"op":225,"ip":0,"assets":[{"nm":"","id":"comp_0","layers":[{"ty":4,"nm":"Shape Layer 1","sr":1,"st":118,"op":3718,"ip":118,"hd":false,"ddd":0,"bm":0,"hasMask":false,"ao":0,"ks":{"a":{"a":0,"k":[0,0,0],"ix":1},"s":{"a":1,"k":[{"o":{"x":0.803,"y":0},"i":{"x":0.184,"y":1},"s":[0,0,100],"t":325},{"o":{"x":0.167,"y":0.167},"i":{"x":0.833,"y":0.833},"s":[110,110,100],"t":365},{"o":{"x":0.764,"y":0},"i":{"x":0.188,"y":1},"s":[110,110,100],"t":388},{"s":[220,220,100],"t":421}],"ix":6},"sk":{"a":0,"k":0},"p":{"a":0,"k":[957.789,535.789,0],"ix":2},"r":{"a":1,"k":[{"o":{"x":0.609,"y":0},"i":{"x":0.399,"y":1},"s":[-45],"t":325},{"s":[0],"t":365}],"ix":10},"sa":{"a":0,"k":0},"o":{"a":0,"k":100,"ix":11}},"ef":[],"shapes":[{"ty":"gr","bm":0,"hd":false,"mn":"ADBE Vector Group","nm":"Rectangle 1","ix":1,"cix":2,"np":3,"it":[{"ty":"rc","bm":0,"hd":false,"mn":"ADBE Vector Shape - Rect","nm":"Rectangle Path 1","d":1,"p":{"a":0,"k":[0,0],"ix":3},"r":{"a":0,"k":14,"ix":4},"s":{"a":0,"k":[68.422,68.422],"ix":2}},{"ty":"fl","bm":0,"hd":false,"mn":"ADBE Vector Graphic - Fill","nm":"Fill 1","c":{"a":0,"k":[0.9569,0.9569,0.9569],"ix":4},"r":1,"o":{"a":0,"k":100,"ix":5}},{"ty":"tr","a":{"a":0,"k":[0,0],"ix":1},"s":{"a":0,"k":[100,100],"ix":3},"sk":{"a":0,"k":0,"ix":4},"p":{"a":0,"k":[2.211,4.211],"ix":2},"r":{"a":0,"k":45,"ix":6},"sa":{"a":0,"k":0,"ix":5},"o":{"a":0,"k":100,"ix":7}}]}],"ind":1},{"ty":4,"nm":"Main logo","sr":1,"st":211,"op":3811,"ip":317,"hd":false,"ddd":0,"bm":0,"hasMask":false,"ao":0,"ks":{"a":{"a":0,"k":[75,75,0],"ix":1},"s":{"a":1,"k":[{"o":{"x":0.705,"y":0},"i":{"x":0.188,"y":1},"s":[100,100,100],"t":388},{"s":[90,90,100],"t":421}],"ix":6},"sk":{"a":0,"k":0},"p":{"a":0,"k":[960,540,0],"ix":2},"r":{"a":1,"k":[{"o":{"x":0.608,"y":0},"i":{"x":0.399,"y":1},"s":[0],"t":325},{"s":[45],"t":365}],"ix":10},"sa":{"a":0,"k":0},"o":{"a":0,"k":100,"ix":11}},"ef":[],"shapes":[{"ty":"gr","bm":0,"hd":false,"mn":"ADBE Vector Group","nm":"Un3ion","ix":1,"cix":2,"np":3,"it":[{"ty":"sh","bm":0,"hd":false,"mn":"ADBE Vector Shape - Group","nm":"Path 1","ix":1,"d":1,"ks":{"a":0,"k":{"c":true,"i":[[0,10.938],[-4.209,9.37],[-3.652,0],[0,0],[0,8.284],[0,0],[-3.331,1.496],[-10.938,0],[-9.371,-4.209],[0,-3.652],[0,0],[-8.284,0],[0,0],[-1.497,-3.331],[0,-10.938],[4.209,-9.37],[3.652,0],[0,0],[0,-8.284],[0,0],[3.331,-1.497],[10.938,0],[9.37,4.209],[0,3.652],[0,0],[8.284,0],[0,0],[1.496,3.331]],"o":[[0,-10.938],[1.496,-3.331],[0,0],[8.284,0],[0,0],[0,-3.652],[9.37,-4.209],[10.938,0],[3.331,1.496],[0,0],[0,8.284],[0,0],[3.652,0],[4.209,9.37],[0,10.938],[-1.497,3.331],[0,0],[-8.284,0],[0,0],[0,3.652],[-9.371,4.209],[-10.938,0],[-3.331,-1.497],[0,0],[0,-8.284],[0,0],[-3.652,0],[-4.209,-9.37]],"v":[[0,75],[6.551,44.3],[15.111,39],[24,39],[39,24],[39,15.111],[44.3,6.551],[75,0],[105.7,6.551],[111,15.111],[111,24],[126,39],[134.889,39],[143.45,44.3],[150,75],[143.45,105.7],[134.889,111],[126,111],[111,126],[111,134.889],[105.7,143.45],[75,150],[44.3,143.45],[39,134.889],[39,126],[24,111],[15.111,111],[6.551,105.7]]},"ix":2}},{"ty":"fl","bm":0,"hd":false,"mn":"ADBE Vector Graphic - Fill","nm":"Fill 1","c":{"a":0,"k":[0.0667,0.0667,0.0667],"ix":4},"r":1,"o":{"a":0,"k":100,"ix":5}},{"ty":"tr","a":{"a":0,"k":[0,0],"ix":1},"s":{"a":0,"k":[100,100],"ix":3},"sk":{"a":0,"k":0,"ix":4},"p":{"a":0,"k":[0,0],"ix":2},"r":{"a":0,"k":0,"ix":6},"sa":{"a":0,"k":0,"ix":5},"o":{"a":0,"k":100,"ix":7}}]}],"ind":2},{"ty":4,"nm":"Ellipse 2","sr":1,"st":285,"op":3885,"ip":284,"hd":false,"ddd":0,"bm":0,"hasMask":false,"ao":0,"ks":{"a":{"a":0,"k":[0,0,0],"ix":1},"s":{"a":0,"k":[100,100,100],"ix":6},"sk":{"a":0,"k":0},"p":{"a":0,"k":[960,540,0],"ix":2},"r":{"a":1,"k":[{"o":{"x":0.167,"y":0.167},"i":{"x":0.833,"y":0.833},"s":[0],"t":351},{"s":[45],"t":403}],"ix":10},"sa":{"a":0,"k":0},"o":{"a":1,"k":[{"o":{"x":0.167,"y":0.167},"i":{"x":0.833,"y":0.833},"s":[100],"t":317},{"s":[0],"t":318}],"ix":11}},"ef":[],"shapes":[{"ty":"gr","bm":0,"hd":false,"mn":"ADBE Vector Group","nm":"Ellipse 1","ix":1,"cix":2,"np":3,"it":[{"ty":"sh","bm":0,"hd":false,"mn":"ADBE Vector Shape - Group","nm":"Path 1","ix":1,"d":1,"ks":{"a":1,"k":[{"o":{"x":0.601,"y":0},"i":{"x":0.392,"y":1},"s":[{"c":true,"i":[[0,10.355],[-0.999,4.882],[-1.898,4.486],[-2.696,3.99],[-3.393,3.393],[-3.99,2.696],[-4.486,1.898],[-4.882,0.999],[-5.178,0],[-4.882,-0.999],[-4.486,-1.898],[-3.99,-2.696],[-3.393,-3.393],[-2.696,-3.99],[-1.898,-4.486],[-0.999,-4.882],[0,-5.178],[0.999,-4.882],[1.898,-4.486],[2.696,-3.99],[3.393,-3.393],[3.99,-2.696],[4.486,-1.898],[4.882,-0.999],[5.178,0],[8.973,3.795],[6.786,6.786],[3.795,8.973]],"o":[[0,-5.178],[0.999,-4.882],[1.898,-4.486],[2.696,-3.99],[3.393,-3.393],[3.99,-2.696],[4.486,-1.898],[4.882,-0.999],[5.178,0],[4.882,0.999],[4.486,1.898],[3.99,2.696],[3.393,3.393],[2.696,3.99],[1.898,4.486],[0.999,4.882],[0,5.178],[-0.999,4.882],[-1.898,4.486],[-2.696,3.99],[-3.393,3.393],[-3.99,2.696],[-4.486,1.898],[-4.882,0.999],[-10.355,0],[-8.973,-3.795],[-6.786,-6.786],[-3.795,-8.973]],"v":[[-75,0],[-73.476,-15.115],[-69.106,-29.193],[-62.191,-41.933],[-53.033,-53.033],[-41.933,-62.191],[-29.193,-69.106],[-15.115,-73.476],[0,-75],[15.115,-73.476],[29.193,-69.106],[41.933,-62.191],[53.033,-53.033],[62.191,-41.933],[69.106,-29.193],[73.476,-15.115],[75,0],[73.476,15.115],[69.106,29.193],[62.191,41.933],[53.033,53.033],[41.933,62.191],[29.193,69.106],[15.115,73.476],[0,75],[-29.193,69.106],[-53.033,53.033],[-69.106,29.193]]}],"t":284},{"s":[{"c":true,"i":[[0,10.938],[-4.209,9.37],[-3.652,0],[0,0],[0,8.284],[0,0],[-3.331,1.496],[-10.938,0],[-9.371,-4.209],[0,-3.652],[0,0],[-8.284,0],[0,0],[-1.497,-3.331],[0,-10.938],[4.209,-9.37],[3.652,0],[0,0],[0,-8.284],[0,0],[3.331,-1.497],[10.938,0],[9.37,4.209],[0,3.652],[0,0],[8.284,0],[0,0],[1.496,3.331]],"o":[[0,-10.938],[1.496,-3.331],[0,0],[8.284,0],[0,0],[0,-3.652],[9.37,-4.209],[10.938,0],[3.331,1.496],[0,0],[0,8.284],[0,0],[3.652,0],[4.209,9.37],[0,10.938],[-1.497,3.331],[0,0],[-8.284,0],[0,0],[0,3.652],[-9.371,4.209],[-10.938,0],[-3.331,-1.497],[0,0],[0,-8.284],[0,0],[-3.652,0],[-4.209,-9.37]],"v":[[-75.25,0.25],[-68.699,-30.45],[-60.139,-35.75],[-51.25,-35.75],[-36.25,-50.75],[-36.25,-59.639],[-30.95,-68.199],[-0.25,-74.75],[30.45,-68.199],[35.75,-59.639],[35.75,-50.75],[50.75,-35.75],[59.639,-35.75],[68.2,-30.45],[74.75,0.25],[68.2,30.95],[59.639,36.25],[50.75,36.25],[35.75,51.25],[35.75,60.139],[30.45,68.7],[-0.25,75.25],[-30.95,68.7],[-36.25,60.139],[-36.25,51.25],[-51.25,36.25],[-60.139,36.25],[-68.699,30.95]]}],"t":317}],"ix":2}},{"ty":"fl","bm":0,"hd":false,"mn":"ADBE Vector Graphic - Fill","nm":"Fill 1","c":{"a":0,"k":[0.0667,0.0667,0.0667],"ix":4},"r":1,"o":{"a":0,"k":100,"ix":5}},{"ty":"tr","a":{"a":0,"k":[0,0],"ix":1},"s":{"a":0,"k":[100,100],"ix":3},"sk":{"a":0,"k":0,"ix":4},"p":{"a":0,"k":[0,0],"ix":2},"r":{"a":0,"k":0,"ix":6},"sa":{"a":0,"k":0,"ix":5},"o":{"a":0,"k":100,"ix":7}}]}],"ind":3},{"ty":4,"nm":"Rectangle 4","sr":1,"st":250,"op":284,"ip":0,"hd":false,"ddd":0,"bm":0,"hasMask":false,"ao":0,"ks":{"a":{"a":0,"k":[0,0,0],"ix":1},"s":{"a":0,"k":[100,100,100],"ix":6},"sk":{"a":0,"k":0},"p":{"a":0,"k":[960,540,0],"ix":2},"r":{"a":1,"k":[{"o":{"x":0.167,"y":0.167},"i":{"x":0.833,"y":0.833},"s":[0],"t":377},{"s":[45],"t":407}],"ix":10},"sa":{"a":0,"k":0},"o":{"a":0,"k":100,"ix":11}},"ef":[],"shapes":[{"ty":"gr","bm":0,"hd":false,"mn":"ADBE Vector Group","nm":"Rectangle 4","ix":1,"cix":2,"np":3,"it":[{"ty":"sh","bm":0,"hd":false,"mn":"ADBE Vector Shape - Group","nm":"Path 1","ix":1,"d":1,"ks":{"a":1,"k":[{"o":{"x":0.612,"y":0},"i":{"x":0.391,"y":1},"s":[{"c":true,"i":[[0,0],[0,0],[0,0],[0,0]],"o":[[0,0],[0,0],[0,0],[0,0]],"v":[[-75,-75],[75,-75],[75,75],[-75,75]]}],"t":250},{"s":[{"c":true,"i":[[0,41.421],[-41.421,0],[0,-41.421],[41.421,0]],"o":[[0,-41.421],[41.421,0],[0,41.421],[-41.421,0]],"v":[[-75,0],[0,-75],[75,0],[0,75]]}],"t":284}],"ix":2}},{"ty":"fl","bm":0,"hd":false,"mn":"ADBE Vector Graphic - Fill","nm":"Fill 1","c":{"a":0,"k":[0.0667,0.0667,0.0667],"ix":4},"r":1,"o":{"a":0,"k":100,"ix":5}},{"ty":"tr","a":{"a":0,"k":[0,0],"ix":1},"s":{"a":0,"k":[100,100],"ix":3},"sk":{"a":0,"k":0,"ix":4},"p":{"a":0,"k":[0,0],"ix":2},"r":{"a":0,"k":0,"ix":6},"sa":{"a":0,"k":0,"ix":5},"o":{"a":0,"k":100,"ix":7}}]}],"ind":4}]}]}